taskhuddler/__init__.py
taskhuddler/graph.py
taskhuddler/task.py
taskhuddler/utils.py
taskhuddler/aio/__init__.py
taskhuddler/aio/graph.py
taskhuddler/aio/nightly.py
taskhuddler/aio/task.py
taskhuddler/aio/utils.py
taskhuddler/test/test_aio_graph.py
taskhuddler/test/test_aio_task.py
taskhuddler/test/test_graph.py
taskhuddler/test/test_task.py
taskhuddler/test/test_utils.py
taskhuddler/test/data/completed.json
taskhuddler/test/data/continuation1.json
taskhuddler/test/data/continuation2.json
taskhuddler/test/data/dummyfile.txt
taskhuddler/test/data/failed.json
taskhuddler/test/data/missing.json
taskhuddler/test/data/unscheduled.json
taskhuddler-0.5.0.dist-info/LICENSE
taskhuddler-0.5.0.dist-info/METADATA
taskhuddler-0.5.0.dist-info/WHEEL
taskhuddler-0.5.0.dist-info/top_level.txt
taskhuddler-0.5.0.dist-info/RECORD
